onto2nx/__init__.py
onto2nx/aba.py
onto2nx/api.py
onto2nx/constants.py
onto2nx/nx2onto.py
onto2nx/owl_rdf.py
onto2nx/owl_xml.py
onto2nx/utils.py
onto2nx/ontospy/__init__.py
onto2nx/ontospy/core/__init__.py
onto2nx/ontospy/core/entities.py
onto2nx/ontospy/core/loader.py
onto2nx/ontospy/core/manager.py
onto2nx/ontospy/core/ontospy.py
onto2nx/ontospy/core/queryHelper.py
onto2nx/ontospy/core/utils.py
onto2nx-0.1.1.dist-info/LICENSE
onto2nx-0.1.1.dist-info/METADATA
onto2nx-0.1.1.dist-info/WHEEL
onto2nx-0.1.1.dist-info/top_level.txt
onto2nx-0.1.1.dist-info/RECORD
