Metadata-Version: 2.1
Name: onto2nx
Version: 0.1.1
Summary: A package for parsing ontologies in the OWL and OBO format into NetworkX graphs
Home-page: https://github.com/cthoyt/onto2nx
Author: Charles Tapley Hoyt and Aliaksandr Masny
Author-email: cthoyt@gmail.com
Maintainer: Charles Tapley Hoyt
Maintainer-email: cthoyt@gmail.com
License: GPL 3.0 License
Keywords: Ontologies,Controlled Vocabularies
Platform: UNKNOWN
Classifier: Development Status :: 1 - Planning
Classifier: Environment :: Console
Classifier: Intended Audience :: Developers
Classifier: Intended Audience :: Science/Research
Classifier: License :: OSI Approved :: GNU General Public License v3 or later (GPLv3+)
Classifier: Operating System :: OS Independent
Classifier: Programming Language :: Python
Classifier: Programming Language :: Python :: 2.7
Classifier: Programming Language :: Python :: 3.6
Classifier: Topic :: Scientific/Engineering :: Bio-Informatics
Requires-Dist: networkx (==1.11)
Requires-Dist: rdflib (==4.2.1)
Requires-Dist: rdflib-jsonld
Requires-Dist: requests
Requires-Dist: requests-file
Requires-Dist: SPARQLWrapper
Requires-Dist: click
Provides-Extra: nx2onto
Requires-Dist: owlready; extra == 'nx2onto'
